framework/__init__.py
framework/core/__init__.py
framework/core/feeder.py
framework/core/hailgraph.py
framework/core/hailstorm.py
hailstorms/__init__.py
hailstorms-1.1.0.dist-info/METADATA
hailstorms-1.1.0.dist-info/WHEEL
hailstorms-1.1.0.dist-info/top_level.txt
hailstorms-1.1.0.dist-info/RECORD
